pint_xarray/__init__.py
pint_xarray/_expects.py
pint_xarray/accessors.py
pint_xarray/compat.py
pint_xarray/conversion.py
pint_xarray/errors.py
pint_xarray/formatting.py
pint_xarray/index.py
pint_xarray/itertools.py
pint_xarray/testing.py
pint_xarray/tests/__init__.py
pint_xarray/tests/test_accessors.py
pint_xarray/tests/test_conversion.py
pint_xarray/tests/test_expects.py
pint_xarray/tests/test_formatting.py
pint_xarray/tests/test_index.py
pint_xarray/tests/test_itertools.py
pint_xarray/tests/test_testing.py
pint_xarray/tests/utils.py
pint_xarray-0.6.0.dist-info/licenses/LICENSE
pint_xarray-0.6.0.dist-info/METADATA
pint_xarray-0.6.0.dist-info/WHEEL
pint_xarray-0.6.0.dist-info/top_level.txt
pint_xarray-0.6.0.dist-info/RECORD
