Metadata-Version: 2.4
Name: pint-xarray
Version: 0.6.0
Summary: Physical units interface to xarray using Pint
Author-email: Tom Nicholas <tomnicholas1@googlemail.com>
License-Expression: Apache-2.0
Project-URL: Home, https://github.com/xarray-contrib/pint-xarray
Project-URL: Documentation, https://pint-xarray.readthedocs.io/en/stable
Classifier: Development Status :: 3 - Alpha
Classifier: Environment :: Console
Classifier: Intended Audience :: Science/Research
Classifier: Operating System :: OS Independent
Classifier: Programming Language :: Python
Classifier: Programming Language :: Python :: 3.11
Classifier: Programming Language :: Python :: 3.12
Classifier: Programming Language :: Python :: 3.13
Classifier: Topic :: Scientific/Engineering
Requires-Python: >=3.11
License-File: LICENSE
Requires-Dist: xarray>=2023.07.0
Requires-Dist: numpy>=1.26
Requires-Dist: pint>=0.24
Dynamic: license-file
